XRO/__init__.py
XRO/core.py
XRO/stats.py
XRO/visual.py
xro-1.0.1.dist-info/licenses/LICENSE
xro-1.0.1.dist-info/METADATA
xro-1.0.1.dist-info/WHEEL
xro-1.0.1.dist-info/top_level.txt
xro-1.0.1.dist-info/RECORD
