Metadata-Version: 2.4
Name: XRO
Version: 1.0.1
Summary: The eXtended nonlinear Recharge Oscillator (XRO) model for ENSO and pantropical climate variability.
Author-email: Sen Zhao <zhaos@hawaii.edu>
License: CC-BY-4.0
Project-URL: Homepage, https://github.com/senclimate/XRO
Project-URL: Documentation, https://senzhao.netlify.app/software/xro/
Project-URL: Repository, https://github.com/senclimate/XRO
Project-URL: Issues, https://github.com/senclimate/XRO/issues
Requires-Python: >=3.9
License-File: LICENSE
Requires-Dist: numpy>=1.20
Requires-Dist: xarray>=2023.1.0
Requires-Dist: matplotlib>=3.5
Dynamic: license-file
